lenient_string_formatter/__init__.py
lenient_string_formatter/_disposable_lenient_formatter.py
lenient_string_formatter/_missing.py
lenient_string_formatter/py.typed
lenient_string_formatter-1.1.2.dist-info/LICENSE
lenient_string_formatter-1.1.2.dist-info/METADATA
lenient_string_formatter-1.1.2.dist-info/WHEEL
lenient_string_formatter-1.1.2.dist-info/RECORD
