Metadata-Version: 2.1
Name: lenient-string-formatter
Version: 1.1.2
Summary: A lenient string formatter that leaves unmatched fields untouched in the output string instead of raising a KeyError.
Home-page: https://github.com/abrahammurciano/python-lenient-string-formatter
License: GPLv3
Author: Abraham Murciano
Author-email: abrahammurciano@gmail.com
Requires-Python: >=3.11
Classifier: License :: Other/Proprietary License
Classifier: Programming Language :: Python :: 3
Classifier: Programming Language :: Python :: 3.11
Classifier: Programming Language :: Python :: 3.12
Project-URL: Documentation, https://abrahammurciano.github.io/python-lenient-string-formatter/lenient-string-formatter
Project-URL: Repository, https://github.com/abrahammurciano/python-lenient-string-formatter
